creedsolo.cp310-win_amd64.pyd
reedsolo.py
tests/perf.py
tests/test_creedsolo.py
tests/test_reedsolo.py
reedsolo-2.0.13.dist-info/LICENSE
reedsolo-2.0.13.dist-info/METADATA
reedsolo-2.0.13.dist-info/WHEEL
reedsolo-2.0.13.dist-info/top_level.txt
reedsolo-2.0.13.dist-info/RECORD
