Metadata-Version: 2.1
Name: reedsolo
Version: 2.0.13
Summary: Pure-Python Universal Errors And Erasures Reed-Solomon Encoder and Decoder
Author: Tomer Filiba
Author-email: Tomer Filiba <tomerfiliba@gmail.com>, Stephen Karl Larroque <lrq3000@gmail.com>
Maintainer: Stephen Karl Larroque
Maintainer-email: Stephen Karl Larroque <lrq3000@gmail.com>
License: The software is available under your choice of
Project-URL: Homepage, https://github.com/tomerfiliba/reedsolomon
Project-URL: Documentation, https://github.com/tomerfiliba/reedsolomon/blob/master/README.rst
Project-URL: Source, https://github.com/tomerfiliba/reedsolomon
Project-URL: Tracker, https://github.com/tomerfiliba/reedsolomon/issues
Project-URL: Download, https://github.com/tomerfiliba/reedsolomon/releases
Project-URL: Conda-Forge, https://anaconda.org/conda-forge/reedsolo
Project-URL: Gentoo, https://packages.gentoo.org/packages/dev-python/reedsolomon
Keywords: data,protection,correction,recovery,restore,save,data-recovery,reed-solomon,error-correction-code,qr,qr-codes,barcodes
Platform: any
Classifier: Development Status :: 6 - Mature
Classifier: Intended Audience :: Developers
Classifier: Intended Audience :: Information Technology
Classifier: License :: OSI Approved :: The Unlicense (Unlicense)
Classifier: License :: OSI Approved :: MIT No Attribution License (MIT-0)
Classifier: Operating System :: Microsoft :: Windows
Classifier: Operating System :: MacOS :: MacOS X
Classifier: Operating System :: POSIX :: Linux
Classifier: Programming Language :: Python :: 2.7
Classifier: Programming Language :: Python :: 3
Classifier: Programming Language :: Python :: 3.7
Classifier: Programming Language :: Python :: 3.8
Classifier: Programming Language :: Python :: 3.9
Classifier: Programming Language :: Python :: 3.10
Classifier: Programming Language :: Python :: 3.11
Classifier: Programming Language :: Python :: 3.12
Classifier: Programming Language :: Python :: Implementation :: PyPy
Classifier: Programming Language :: Cython
Classifier: Topic :: Communications
Classifier: Topic :: Scientific/Engineering :: Mathematics
Classifier: Topic :: System :: Archiving :: Backup
Classifier: Topic :: System :: Recovery Tools
Requires-Python: >=2.7
License-File: LICENSE
